html2py/__init__.py
html2py/converter.py
html2py/output.py
html2py/parser.py
html2py/yattag.py
html2py-1.0.1.data/scripts/html2py.py
html2py-1.0.1.dist-info/DESCRIPTION.rst
html2py-1.0.1.dist-info/METADATA
html2py-1.0.1.dist-info/RECORD
html2py-1.0.1.dist-info/WHEEL
html2py-1.0.1.dist-info/metadata.json
html2py-1.0.1.dist-info/top_level.txt
