Metadata-Version: 2.0
Name: html2py
Version: 1.0.1
Summary: html2py is a tool for converting an html file in python language and viceversa.
Home-page: http://gitlab.com/trollodel/html2py
Author: trollodel
Author-email: UNKNOWN
License: LGPLv2.1
Keywords: yattag generation html2py code_generator tool
Platform: UNKNOWN
Requires-Dist: lxml
Requires-Dist: yattag
